scenario_integration/__init__.py
scenario_integration/cli.py
scenario_integration/core.py
scenario_integration/paths.py
scenario_integration-0.1.0.dist-info/METADATA
scenario_integration-0.1.0.dist-info/WHEEL
scenario_integration-0.1.0.dist-info/top_level.txt
scenario_integration-0.1.0.dist-info/RECORD
